tailor/__init__.py
tailor/tailor_wrapper.py
tailor/version.py
tailor/common/__init__.py
tailor/common/abstractions.py
tailor/common/perturb_function.py
tailor/common/perturbation_criteria.py
tailor/common/testing.py
tailor/common/utils/__init__.py
tailor/common/utils/controls.py
tailor/common/utils/detect_perturbations.py
tailor/common/utils/generate_utils.py
tailor/common/utils/head_prompt_utils.py
tailor/common/utils/model_utils.py
tailor/common/utils/perturbation_controls.py
tailor/common/utils/tag_utils.py
tailor/steps/__init__.py
tailor/steps/combine_all_prompts.py
tailor/steps/convert_dataset_to_dict.py
tailor/steps/generate_from_prompts.py
tailor/steps/get_sentences.py
tailor/steps/get_srl_tags.py
tailor/steps/load_generator.py
tailor/steps/perturb_prompt.py
tailor/steps/process_with_spacy.py
tailor/steps/random_prompts.py
tailor/steps/validate_generations.py
tailor/tasks/__init__.py
tailor/tasks/nli/__init__.py
tailor/tasks/nli/augment.py
tailor/tasks/nli/convert_dataset_to_dict.py
tailor/tasks/nli/perturbations.py
tailor/tasks/qa/__init__.py
tailor_nlp-0.1.0.dist-info/LICENSE
tailor_nlp-0.1.0.dist-info/METADATA
tailor_nlp-0.1.0.dist-info/WHEEL
tailor_nlp-0.1.0.dist-info/top_level.txt
tailor_nlp-0.1.0.dist-info/RECORD
