Metadata-Version: 2.1
Name: tailor-nlp
Version: 0.1.0
Summary: UNKNOWN
Home-page: https://github.com/allenai/tailor
Author: Allen Institute for Artificial Intelligence
Author-email: contact@allenai.org
License: Apache
Platform: UNKNOWN
Classifier: Intended Audience :: Science/Research
Classifier: Development Status :: 3 - Alpha
Classifier: License :: OSI Approved :: Apache Software License
Classifier: Programming Language :: Python :: 3
Classifier: Topic :: Scientific/Engineering :: Artificial Intelligence
Requires-Python: >=3.6.1
License-File: LICENSE
Requires-Dist: ai2-tango[datasets] (>=0.4.0)
Requires-Dist: spacy (<=3.1.4)
Requires-Dist: allennlp-models (==2.9.0)
Requires-Dist: stanford-openie (==1.0.3)
Requires-Dist: transformers (<=4.4.2)
Requires-Dist: datasets (==1.15.1)
Requires-Dist: munch (==2.5.0)
Requires-Dist: checklist
